utg_base/__init__.py
utg_base/api/__init__.py
utg_base/api/base.py
utg_base/api/pagination.py
utg_base/api/permissions.py
utg_base/api/routers.py
utg_base/api/serializers.py
utg_base/api/spectacular.py
utg_base/authentications/__init__.py
utg_base/authentications/microservice_authentication.py
utg_base/authentications/models.py
utg_base/celery/__init__.py
utg_base/celery/apps.py
utg_base/celery/filters/__init__.py
utg_base/celery/filters/task_result.py
utg_base/celery/management/__init__.py
utg_base/celery/management/commands/__init__.py
utg_base/celery/management/commands/migrate_tasks.py
utg_base/celery/serializers/__init__.py
utg_base/celery/serializers/periodic_task.py
utg_base/celery/serializers/task_result.py
utg_base/celery/urls.py
utg_base/celery/views/__init__.py
utg_base/celery/views/periodic_task.py
utg_base/celery/views/task_result.py
utg_base/constants/__init__.py
utg_base/constants/accessibility_type.py
utg_base/constants/available_languages.py
utg_base/env.py
utg_base/logging.py
utg_base/middleware/__init__.py
utg_base/middleware/debug.py
utg_base/middleware/locale.py
utg_base/migration/__init__.py
utg_base/migration/apps.py
utg_base/migration/management/__init__.py
utg_base/migration/management/commands/__init__.py
utg_base/migration/management/commands/makemigrations.py
utg_base/models/__init__.py
utg_base/models/jwt_user.py
utg_base/models/timestamp.py
utg_base/permissions/__init__.py
utg_base/permissions/decorators.py
utg_base/permissions/folder.py
utg_base/permissions/utils.py
utg_base/references_api/__init__.py
utg_base/references_api/apps.py
utg_base/references_api/migrations/__init__.py
utg_base/references_api/urls.py
utg_base/references_api/utils.py
utg_base/services/__init__.py
utg_base/services/base_api.py
utg_base/signals/__init__.py
utg_base/signals/sync_perms.py
utg_base/u_services/__init__.py
utg_base/u_services/apps.py
utg_base/u_services/constants.py
utg_base/u_services/migrations/0001_initial.py
utg_base-1.21.2.dist-info/METADATA
utg_base-1.21.2.dist-info/WHEEL
utg_base-1.21.2.dist-info/RECORD
