Metadata-Version: 2.1
Name: utg-base
Version: 1.21.2
Summary: UTG Base Package
Author: Olimboy
Author-email: shavkatov.olimboy@mail.ru
Requires-Python: >=3.14,<4.0
Classifier: Programming Language :: Python :: 3
Requires-Dist: celery (>=5.5.3,<6.0.0)
Requires-Dist: croniter (>=2.0.3,<3.0.0)
Requires-Dist: django (>=5.2.7,<6.0.0)
Requires-Dist: django-celery-beat (>=2.8.1,<3.0.0)
Requires-Dist: django-celery-results (>=2.6.0,<3.0.0)
Requires-Dist: django-filter (>=23.5,<24.0)
Requires-Dist: django-redis (>=6.0.0,<7.0.0)
Requires-Dist: djangorestframework (>=3.16.1,<4.0.0)
Requires-Dist: djangorestframework-simplejwt[crypto] (>=5.5.1,<6.0.0)
Requires-Dist: dotenv (>=0.9.9,<0.10.0)
Requires-Dist: drf-spectacular[sidecar] (>=0.29.0,<0.30.0)
Requires-Dist: environs (>=14.5.0,<15.0.0)
Requires-Dist: hvac (>=2.4.0,<3.0.0)
Requires-Dist: inflect (>=7.2.1,<8.0.0)
Requires-Dist: openpyxl (>=3.1.2,<4.0.0)
